cmad/__init__.py
cmad/cmad_exact.py
cmad-0.1.0.post6.dist-info/METADATA
cmad-0.1.0.post6.dist-info/WHEEL
cmad-0.1.0.post6.dist-info/top_level.txt
cmad-0.1.0.post6.dist-info/RECORD
