Metadata-Version: 2.4
Name: cmad
Version: 0.1.0.post6
Summary: CMAD: A Lightweight Framework for Extreme Spatio-Temporal Anomaly Detection
Author: Maloy Kumar Devnath, Sudip Chakraborty, Vandana P. Janeja
License: iHARP
Project-URL: Homepage, https://github.com/bitsbytes-maker/cmad
Project-URL: Source, https://github.com/bitsbytes-maker/cmad
Project-URL: Issues, https://github.com/bitsbytes-maker/cmad/issues
Project-URL: Paper, https://doi.org/10.1145/3678717.3691280
Keywords: cmad,convolution matrix anomaly detection,clusters of anomalous events detection,anomaly detection,extreme event detection,spatio temporal anomaly detection,spatio temporal data mining,geospatial,geoai,climate,cryosphere,unsupervised learning,machine learning,data science
Classifier: Development Status :: 3 - Alpha
Classifier: Intended Audience :: Science/Research
Classifier: Topic :: Scientific/Engineering
Classifier: Topic :: Scientific/Engineering :: Artificial Intelligence
Classifier: Topic :: Scientific/Engineering :: Information Analysis
Classifier: Topic :: Scientific/Engineering :: GIS
Classifier: Topic :: Scientific/Engineering :: Atmospheric Science
Classifier: Topic :: Software Development :: Libraries :: Python Modules
Classifier: Programming Language :: Python :: 3
Classifier: Programming Language :: Python :: 3 :: Only
Classifier: Operating System :: OS Independent
Requires-Python: >=3.8
Requires-Dist: numpy
Requires-Dist: torch
Requires-Dist: opencv-python
Requires-Dist: matplotlib
